setup.cfg
setup.py
common_ops.egg-info/PKG-INFO
common_ops.egg-info/SOURCES.txt
common_ops.egg-info/dependency_links.txt
common_ops.egg-info/not-zip-safe
common_ops.egg-info/requires.txt
common_ops.egg-info/top_level.txt
ops/__init__.py
ops/args.py
ops/dingdingapi.py
ops/git.py
ops/notification.py
ops/timeout.py
ops/version.py